pyportable_crypto/__init__.py
pyportable_crypto/__main__.py
pyportable_crypto/cipher_gen/__init__.py
pyportable_crypto/cipher_gen/_cache/.gitkeep
pyportable_crypto/cipher_gen/cipher_standalone.py
pyportable_crypto/cipher_gen/cythonize.py
pyportable_crypto/cipher_gen/generator.py
pyportable_crypto/cipher_gen/site-packages.zip
pyportable_crypto/compilation/__init__.py
pyportable_crypto/compilation/api.py
pyportable_crypto/compilation/compiler.py
pyportable_crypto/encryption/__init__.py
pyportable_crypto/encryption/_pyaes_snippet.py
pyportable_crypto/encryption/decrypt.py
pyportable_crypto/encryption/encrypt.py
pyportable_crypto/encryption/formatter.py
pyportable_crypto/encryption/keygen.py
pyportable_crypto-1.5.0.dist-info/LICENSE
pyportable_crypto-1.5.0.dist-info/METADATA
pyportable_crypto-1.5.0.dist-info/WHEEL
pyportable_crypto-1.5.0.dist-info/RECORD
