Metadata-Version: 2.3
Name: pyportable-crypto
Version: 1.5.0
Summary: Crypto plugin for pyportable-installer project.
License: MIT
Author: Likianta
Author-email: likianta@foxmail.com
Requires-Python: >=3.8
Classifier: License :: OSI Approved :: MIT License
Classifier: Programming Language :: Python :: 3
Classifier: Programming Language :: Python :: 3.8
Classifier: Programming Language :: Python :: 3.9
Classifier: Programming Language :: Python :: 3.10
Classifier: Programming Language :: Python :: 3.11
Classifier: Programming Language :: Python :: 3.12
Classifier: Programming Language :: Python :: 3.13
Requires-Dist: argsense (>=1.1.0,<2.0.0)
Requires-Dist: cython (>=3.1.2,<4.0.0)
Requires-Dist: lk-logger (>=6.0.6,<7.0.0)
Requires-Dist: lk-utils (>=3.2.1,<4.0.0)
Requires-Dist: setuptools
Project-URL: Homepage, https://github.com/likianta/pyportable-crypto
